{
  "type": "forge:conditional",
  "recipes": [
    {
      "conditions": [
        {
          "modid": "byg",
          "type": "forge:mod_loaded"
        }
      ],
      "recipe": {
        "type": "minecraft:crafting_shaped",
        "group": "crate",
        "pattern": [
          "LPL",
          "P P",
          "LPL"
        ],
        "key": {
          "L": {
            "item": "byg:green_enchanted_log"
          },
          "P": {
            "item": "byg:green_enchanted_planks"
          }
        },
        "result": {
          "item": "morecfm:byg_green_enchanted_crate",
          "count": 2
        }
      }
    }
  ]
}